setup.py
client/__init__.py
client/client.py
client/client/__init__.py
client/client/client_contact.py
client/client/client_del_contact.py
client/client/client_start_dialog.py
client/client/client_transport.py
client/client/database.py
client/client/main_window.py
client/client/main_window_conv.py
client/common/__init__.py
client/common/decos.py
client/common/descryptors.py
client/common/errors.py
client/common/metaclasses.py
client/common/utils.py
client/common/variables.py
client/logs/__init__.py
client/logs/config_client_log.py
client/logs/config_server_log.py
client/unit_tests/__init__.py
neatek_python_chat_client.egg-info/PKG-INFO
neatek_python_chat_client.egg-info/SOURCES.txt
neatek_python_chat_client.egg-info/dependency_links.txt
neatek_python_chat_client.egg-info/top_level.txt