Metadata-Version: 2.1
Name: neatek-python-chat-client
Version: 0.1
Summary: Client packet
Author: Vladimir Zhelnov
Author-email: neatek@icloud.com
